sarkas/__init__.py
sarkas/core.py
sarkas/processes.py
sarkas/potentials/__init__.py
sarkas/potentials/core.py
sarkas/potentials/coulomb.py
sarkas/potentials/egs.py
sarkas/potentials/force_pm.py
sarkas/potentials/force_pp.py
sarkas/potentials/hs_yukawa.py
sarkas/potentials/lennardjones.py
sarkas/potentials/moliere.py
sarkas/potentials/qsp.py
sarkas/potentials/yukawa.py
sarkas/time_evolution/__init__.py
sarkas/time_evolution/integrators.py
sarkas/time_evolution/thermostats.py
sarkas/tools/__init__.py
sarkas/tools/observables.py
sarkas/tools/transport.py
sarkas/utilities/__init__.py
sarkas/utilities/exceptions.py
sarkas/utilities/io.py
sarkas/utilities/maths.py
sarkas/utilities/timing.py
sarkas-1.0.2.data/scripts/sarkas_simulate
sarkas-1.0.2.dist-info/LICENSE
sarkas-1.0.2.dist-info/METADATA
sarkas-1.0.2.dist-info/WHEEL
sarkas-1.0.2.dist-info/top_level.txt
sarkas-1.0.2.dist-info/RECORD
