Metadata-Version: 2.1
Name: sarkas
Version: 1.0.2
Summary: Sarkas - A Fast pure-python Molecular Dynamics suite for plasmas
Home-page: https://murillogroup.github.io/sarkas
Author: Murillo Group
Author-email: sarkasdev@gmail.com
License: MIT
Platform: UNKNOWN
Classifier: Development Status :: 5 - Production/Stable
Classifier: Intended Audience :: Science/Research
Classifier: Programming Language :: Python :: 3
Classifier: License :: OSI Approved :: MIT License
Classifier: Operating System :: OS Independent
Requires-Python: >=3.7
License-File: LICENSE
Requires-Dist: numpy
Requires-Dist: scipy
Requires-Dist: pandas
Requires-Dist: numba (>=0.50)
Requires-Dist: pyfftw
Requires-Dist: pyyaml
Requires-Dist: tables
Requires-Dist: tqdm
Requires-Dist: pyfiglet (==0.8.post1)
Requires-Dist: pickle5
Requires-Dist: jupyter
Requires-Dist: jupyterlab
Requires-Dist: notebook
Requires-Dist: matplotlib
Requires-Dist: seaborn
